Workbook
Name StartingBalance: Summary!$L$8

Sheet Summary
B2: GET STARTED | I2: NOTE
B3: Set your starting balance in cell L8, then customize your categories and planned spending amounts in the 'Income' and 'Expenses' tables below. | I3: Only edit highlighted cells.
I4: Try not to alter cells that contain a formula.
B5: As you enter data in the 'Transactions' tab, this sheet will automatically update to show a summary of your spending for the month.
B8: Monthly Budget | J8: Starting balance: | L8: 1000
D12: =IFERROR(__xludf.DUMMYFUNCTION("SPARKLINE(D17,{""charttype"",""column"";""ymin"", 0; ""ymax"",MAX(D17:E17);""firstcolor"",""#334960""})"),"") | E12: =IFERROR(__xludf.DUMMYFUNCTION("SPARKLINE(E17,{""charttype"",""column"";""ymin"", 0; ""ymax"",max(D17:E17);""firstcolor"",""#f46524""})"),"")
I13: =iferror(E17/D17-1, "") -> 0.5
I14: =if(I13 < 0, "Decrease in total savings", "Increase in total savings") -> Increase in total savings
I15: =iferror(E17-D17, 0) -> 500
D16: START BALANCE | E16: END BALANCE | I16: =if(J15<0, "Spent this month", "Saved this month") -> Saved this month
D17: =if(isblank(L8),0,L8) -> 1000 | E17: =D17+(I22-C22) -> 1500
B20: Expenses | H20: Income
B21: Planned | C21: =D26 -> 950 | D21: =IFERROR(__xludf.DUMMYFUNCTION("SPARKLINE(C21,{""charttype"",""bar"";""max"",max(C21:C22);""color1"",""#AEB7C0""})"),"") | H21: Planned | I21: =J26 -> 1450 | J21: =IFERROR(__xludf.DUMMYFUNCTION("SPARKLINE(I21,{""charttype"",""bar"";""max"",max(I21:I22);""color1"",""#AEB7C0""})"),"")
B22: Actual | C22: =E26 -> 1000 | D22: =IFERROR(__xludf.DUMMYFUNCTION("SPARKLINE(C22,{""charttype"",""bar"";""max"",max(C21:C22);""color1"",""#334960""})"),"") | H22: Actual | I22: =K26 -> 1500 | J22: =IFERROR(__xludf.DUMMYFUNCTION("SPARKLINE(I22,{""charttype"",""bar"";""max"",max(I21:I22);""color1"",""#334960""})"),"")
B24: Expenses | H24: Income
D25: Planned | E25: Actual | F25: Diff. | J25: Planned | K25: Actual | L25: Diff.
B26: Totals | D26: =sum(D27:D44) -> 950 | E26: =sum(E27:E44) -> 1000 | F26: =sum(F27:F44) -> -50 | H26: Totals | J26: =sum(J27:J44) -> 1450 | K26: =sum(K27:K44) -> 1500 | L26: =sum(L27:L44) -> 50
E27: =if(isblank($B27), "", sumif(Transactions!$E:$E,$B27,Transactions!$C:$C)) | F27: =if(isblank($B27), "", D27-E27) | K27: =if(isblank($H27), "", sumif(Transactions!$J:$J,$H27,Transactions!$H:$H)) | L27: =if(isblank($H27), "", K27-J27)
B28: Food | D28: 0 | E28: =if(isblank($B28), "", sumif(Transactions!$E:$E,$B28,Transactions!$C:$C)) -> 0 | F28: =if(isblank($B28), "", D28-E28) -> 0 | H28: Savings | J28: 0 | K28: =if(isblank($H28), "", sumif(Transactions!$J:$J,$H28,Transactions!$H:$H)) -> 0 | L28: =if(isblank($H28), "", K28-J28) -> 0
B29: Gifts | D29: 0 | E29: =if(isblank($B29), "", sumif(Transactions!$E:$E,$B29,Transactions!$C:$C)) -> 0 | F29: =if(isblank($B29), "", D29-E29) -> 0 | H29: Paycheck | J29: 1450 | K29: =if(isblank($H29), "", sumif(Transactions!$J:$J,$H29,Transactions!$H:$H)) -> 1500 | L29: =if(isblank($H29), "", K29-J29) -> 50
B30: Health/medical | D30: 0 | E30: =if(isblank($B30), "", sumif(Transactions!$E:$E,$B30,Transactions!$C:$C)) -> 0 | F30: =if(isblank($B30), "", D30-E30) -> 0 | H30: Bonus | J30: 0 | K30: =if(isblank($H30), "", sumif(Transactions!$J:$J,$H30,Transactions!$H:$H)) -> 0 | L30: =if(isblank($H30), "", K30-J30) -> 0
B31: Home | D31: 950 | E31: =if(isblank($B31), "", sumif(Transactions!$E:$E,$B31,Transactions!$C:$C)) -> 1000 | F31: =if(isblank($B31), "", D31-E31) -> -50 | H31: Interest | J31: 0 | K31: =if(isblank($H31), "", sumif(Transactions!$J:$J,$H31,Transactions!$H:$H)) -> 0 | L31: =if(isblank($H31), "", K31-J31) -> 0
B32: Transportation | D32: 0 | E32: =if(isblank($B32), "", sumif(Transactions!$E:$E,$B32,Transactions!$C:$C)) -> 0 | F32: =if(isblank($B32), "", D32-E32) -> 0 | H32: Other | J32: 0 | K32: =if(isblank($H32), "", sumif(Transactions!$J:$J,$H32,Transactions!$H:$H)) -> 0 | L32: =if(isblank($H32), "", K32-J32) -> 0
B33: Personal | D33: 0 | E33: =if(isblank($B33), "", sumif(Transactions!$E:$E,$B33,Transactions!$C:$C)) -> 0 | F33: =if(isblank($B33), "", D33-E33) -> 0 | H33: Custom category | J33: 0 | K33: =if(isblank($H33), "", sumif(Transactions!$J:$J,$H33,Transactions!$H:$H)) -> 0 | L33: =if(isblank($H33), "", K33-J33) -> 0
B34: Pets | D34: 0 | E34: =if(isblank($B34), "", sumif(Transactions!$E:$E,$B34,Transactions!$C:$C)) -> 0 | F34: =if(isblank($B34), "", D34-E34) -> 0 | K34: =if(isblank($H34), "", sumif(Transactions!$J:$J,$H34,Transactions!$H:$H)) | L34: =if(isblank($H34), "", K34-J34)
B35: Utilities | D35: 0 | E35: =if(isblank($B35), "", sumif(Transactions!$E:$E,$B35,Transactions!$C:$C)) -> 0 | F35: =if(isblank($B35), "", D35-E35) -> 0 | K35: =if(isblank($H35), "", sumif(Transactions!$J:$J,$H35,Transactions!$H:$H)) | L35: =if(isblank($H35), "", K35-J35)
B36: Travel | D36: 0 | E36: =if(isblank($B36), "", sumif(Transactions!$E:$E,$B36,Transactions!$C:$C)) -> 0 | F36: =if(isblank($B36), "", D36-E36) -> 0 | K36: =if(isblank($H36), "", sumif(Transactions!$J:$J,$H36,Transactions!$H:$H)) | L36: =if(isblank($H36), "", K36-J36)
B37: Debt | D37: 0 | E37: =if(isblank($B37), "", sumif(Transactions!$E:$E,$B37,Transactions!$C:$C)) -> 0 | F37: =if(isblank($B37), "", D37-E37) -> 0 | K37: =if(isblank($H37), "", sumif(Transactions!$J:$J,$H37,Transactions!$H:$H)) | L37: =if(isblank($H37), "", K37-J37)
B38: Other | D38: 0 | E38: =if(isblank($B38), "", sumif(Transactions!$E:$E,$B38,Transactions!$C:$C)) -> 0 | F38: =if(isblank($B38), "", D38-E38) -> 0 | K38: =if(isblank($H38), "", sumif(Transactions!$J:$J,$H38,Transactions!$H:$H)) | L38: =if(isblank($H38), "", K38-J38)
B39: Custom category 1 | D39: 0 | E39: =if(isblank($B39), "", sumif(Transactions!$E:$E,$B39,Transactions!$C:$C)) -> 0 | F39: =if(isblank($B39), "", D39-E39) -> 0 | K39: =if(isblank($H39), "", sumif(Transactions!$J:$J,$H39,Transactions!$H:$H)) | L39: =if(isblank($H39), "", K39-J39)
B40: Custom category 2 | D40: 0 | E40: =if(isblank($B40), "", sumif(Transactions!$E:$E,$B40,Transactions!$C:$C)) -> 0 | F40: =if(isblank($B40), "", D40-E40) -> 0 | K40: =if(isblank($H40), "", sumif(Transactions!$J:$J,$H40,Transactions!$H:$H)) | L40: =if(isblank($H40), "", K40-J40)
B41: Custom category 3 | D41: 0 | E41: =if(isblank($B41), "", sumif(Transactions!$E:$E,$B41,Transactions!$C:$C)) -> 0 | F41: =if(isblank($B41), "", D41-E41) -> 0 | K41: =if(isblank($H41), "", sumif(Transactions!$J:$J,$H41,Transactions!$H:$H)) | L41: =if(isblank($H41), "", K41-J41)
E44: =if(isblank($B44), "", sumif(Transactions!$E:$E,$B44,Transactions!$C:$C)) | F44: =if(isblank($B44), "", D44-E44) | K44: =if(isblank($H44), "", sumif(Transactions!$J:$J,$H44,Transactions!$H:$H)) | L44: =if(isblank($H44), "", K44-J44)

Sheet Transactions
B1: Change or add categories by updating the Expenses and Income tables in the Summary sheet.
B2: Expenses | G2: Income
B4: Date | C4: Amount | D4: Description | E4: Category | G4: Date | H4: Amount | I4: Description | J4: Category
B5: 36868 | C5: 1000 | D5: Rent | E5: Home | G5: 36868 | H5: 1500 | I5: Paycheck | J5: Paycheck
